{
  "Titulo": "Inter Miami avança na Copa dos Campeões da Concacaf com vitória sobre Sporting Kansas City",
  "Resumo": "Na noite de terça-feira, vinte e cinco de abril de dois mil e vinte e cinco, o Inter Miami garantiu sua vaga nas oitavas de final da Copa dos Campeões da Concacaf ao vencer o Sporting Kansas City por três a um em casa. Os gols da equipe foram marcados por Lionel Messi e Luis Suárez, que tiveram atuações decisivas na partida. Com esse resultado, o time da Flórida segue firme na competição continental, demonstrando entrosamento e eficiência ofensiva.",
  "Imagem": "https://sdmntprsouthcentralus.oaiusercontent.com/files/00000000-8280-61f7-98bd-510de1aa853e/raw?se=2025-04-25T21%3A25%3A23Z&sp=r&sv=2024-08-04&sr=b&scid=23cc163c-341b-57c0-9a75-875c06d2dca6&skoid=ae70be19-8043-4428-a990-27c58b478304&sktid=a48cca56-e6da-484e-a814-9c849652bcb3&skt=2025-04-25T19%3A57%3A34Z&ske=2025-04-26T19%3A57%3A34Z&sks=b&skv=2024-08-04&sig=gq0RPaeLYl6DXRAu2lAQMW0Owrvw30D/rZMFMD7q2pY%3D",
  "DataInicio": "2025-04-25T17:22:51.1953754-03:00",
  "DataHora": "2025-04-25T17:25:36.2434861-03:00"
}