{
  "Titulo": "Leão – Confiança em Alta e Novas Conexões",
  "Resumo": "Nesta quarta-feira, primeiro de maio, os leoninos sentem um impulso renovado de autoconfiança, favorecendo encontros, conversas e oportunidades de networking. O momento é propício para demonstrar talentos e atrair pessoas que compartilham interesses semelhantes. Evite disputas por atenção e mantenha o foco em parcerias construtivas. A harmonia nas relações se fortalece com atitudes generosas e disposição para ouvir. Siga-nos, compartilhe este vídeo, deixe seu like",
  "Imagem": "https://sdmntpreastus2.oaiusercontent.com/files/00000000-005c-61f6-b139-683c5d1e3f99/raw?se=2025-05-01T15%3A21%3A23Z&sp=r&sv=2024-08-04&sr=b&scid=2461c25b-dd96-5f49-8a40-9d06450b4528&skoid=a47cd303-16a2-427e-8efb-2ce406116005&sktid=a48cca56-e6da-484e-a814-9c849652bcb3&skt=2025-05-01T10%3A39%3A50Z&ske=2025-05-02T10%3A39%3A50Z&sks=b&skv=2024-08-04&sig=SqbgpiC44OvZT9t3zoXsEaG6ieXtyaykAf60x7DZ0hg%3D",
  "DataInicio": "2025-05-01T11:18:45.6369026-03:00",
  "DataHora": "2025-05-01T11:21:38.8189996-03:00"
}